odoo/addons/account_statement_import_online_ponto/README.rst
odoo/addons/account_statement_import_online_ponto/__init__.py
odoo/addons/account_statement_import_online_ponto/__manifest__.py
odoo/addons/account_statement_import_online_ponto/i18n/account_statement_import_online_ponto.pot
odoo/addons/account_statement_import_online_ponto/i18n/ca.po
odoo/addons/account_statement_import_online_ponto/i18n/it.po
odoo/addons/account_statement_import_online_ponto/models/__init__.py
odoo/addons/account_statement_import_online_ponto/models/online_bank_statement_provider_ponto.py
odoo/addons/account_statement_import_online_ponto/readme/CONFIGURE.rst
odoo/addons/account_statement_import_online_ponto/readme/CONTRIBUTORS.rst
odoo/addons/account_statement_import_online_ponto/readme/DESCRIPTION.rst
odoo/addons/account_statement_import_online_ponto/readme/USAGE.rst
odoo/addons/account_statement_import_online_ponto/static/description/icon.png
odoo/addons/account_statement_import_online_ponto/static/description/index.html
odoo/addons/account_statement_import_online_ponto/tests/__init__.py
odoo/addons/account_statement_import_online_ponto/tests/test_account_statement_import_online_ponto.py
odoo/addons/account_statement_import_online_ponto/view/online_bank_statement_provider.xml
odoo14_addon_account_statement_import_online_ponto-14.0.1.1.0.dist-info/METADATA
odoo14_addon_account_statement_import_online_ponto-14.0.1.1.0.dist-info/WHEEL
odoo14_addon_account_statement_import_online_ponto-14.0.1.1.0.dist-info/top_level.txt
odoo14_addon_account_statement_import_online_ponto-14.0.1.1.0.dist-info/RECORD
